safet-0.1.5.data/scripts/safetctl
safetlib/__init__.py
safetlib/ckd_public.py
safetlib/client.py
safetlib/coins.py
safetlib/debuglink.py
safetlib/device.py
safetlib/ed25519cosi.py
safetlib/ed25519raw.py
safetlib/mapping.py
safetlib/protobuf.py
safetlib/protocol_v1.py
safetlib/protocol_v2.py
safetlib/tools.py
safetlib/transport.py
safetlib/transport_bridge.py
safetlib/transport_hid.py
safetlib/transport_udp.py
safetlib/transport_webusb.py
safetlib/tx_api.py
safetlib/messages/Address.py
safetlib/messages/ApplyFlags.py
safetlib/messages/ApplySettings.py
safetlib/messages/BackupDevice.py
safetlib/messages/ButtonAck.py
safetlib/messages/ButtonRequest.py
safetlib/messages/ButtonRequestType.py
safetlib/messages/Cancel.py
safetlib/messages/ChangePin.py
safetlib/messages/CipherKeyValue.py
safetlib/messages/CipheredKeyValue.py
safetlib/messages/ClearSession.py
safetlib/messages/CoinType.py
safetlib/messages/CosiCommit.py
safetlib/messages/CosiCommitment.py
safetlib/messages/CosiSign.py
safetlib/messages/CosiSignature.py
safetlib/messages/DebugLinkDecision.py
safetlib/messages/DebugLinkFlashErase.py
safetlib/messages/DebugLinkGetState.py
safetlib/messages/DebugLinkLog.py
safetlib/messages/DebugLinkMemory.py
safetlib/messages/DebugLinkMemoryRead.py
safetlib/messages/DebugLinkMemoryWrite.py
safetlib/messages/DebugLinkState.py
safetlib/messages/DebugLinkStop.py
safetlib/messages/DecryptMessage.py
safetlib/messages/DecryptedMessage.py
safetlib/messages/ECDHSessionKey.py
safetlib/messages/EncryptMessage.py
safetlib/messages/EncryptedMessage.py
safetlib/messages/Entropy.py
safetlib/messages/EntropyAck.py
safetlib/messages/EntropyRequest.py
safetlib/messages/EstimateTxSize.py
safetlib/messages/EthereumAddress.py
safetlib/messages/EthereumGetAddress.py
safetlib/messages/EthereumMessageSignature.py
safetlib/messages/EthereumSignMessage.py
safetlib/messages/EthereumSignTx.py
safetlib/messages/EthereumTxAck.py
safetlib/messages/EthereumTxRequest.py
safet-0.1.5.dist-info/COPYING
safet-0.1.5.dist-info/METADATA
safet-0.1.5.dist-info/WHEEL
safet-0.1.5.dist-info/top_level.txt
safet-0.1.5.dist-info/RECORD
